num_thai/__init__.py
num_thai/__version__.py
num_thai/thainumbers.py
num_thai-0.0.5.dist-info/METADATA
num_thai-0.0.5.dist-info/RECORD
num_thai-0.0.5.dist-info/WHEEL
num_thai-0.0.5.dist-info/top_level.txt
