Metadata-Version: 2.1
Name: num_thai
Version: 0.0.5
Summary: This convert number to thai text lib
Home-page: https://github.com/pinyoothotaboot/num-thai
Author: Mr.Pinyoo Thotaboot
Author-email: pinyoo.too@gmail.com
License: MIT
Platform: UNKNOWN
Classifier: Development Status :: 4 - Beta
Classifier: Programming Language :: Python :: 3.6
Classifier: License :: OSI Approved :: MIT License
Classifier: Operating System :: OS Independent
Classifier: Intended Audience :: Developers
Classifier: Topic :: Software Development :: Libraries :: Python Modules
Requires-Python: >=3.6
